{"container_type": "Author", "filled": ["basics", "publications", "indices", "counts"], "scholar_id": "lTUM3B0AAAAJ", "source": "AUTHOR_PROFILE_PAGE", "name": "Yanjun Zhu", "url_picture": "https://scholar.googleusercontent.com/citations?view_op=view_photo&user=lTUM3B0AAAAJ&citpid=6", "affiliation": "Research Scientist, Northeastern University", "interests": ["Human Action/Motion/Emotion Analytics", "Human-Centric AI for Health", "Computer Vision for Agriculture"], "email_domain": "@northeastern.edu", "homepage": "http://yjzhux.github.io/", "citedby": 727, "publications": {"lTUM3B0AAAAJ:qjMakFHDy7sC": {"container_type": "Publication", "source": "AUTHOR_PUBLICATION_ENTRY", "bib": {"title": "In-field automatic observation of wheat heading stage using computer vision", "pub_year": "2016"}, "filled": false, "author_pub_id": "lTUM3B0AAAAJ:qjMakFHDy7sC", "num_citations": 142, "citedby_url": "https://scholar.google.com/scholar?oi=bibs&hl=en&cites=9485023216843319938", "cites_id": ["9485023216843319938"]}, "lTUM3B0AAAAJ:u-x6o8ySG0sC": {"container_type": "Publication", "source": "AUTHOR_PUBLICATION_ENTRY", "bib": {"title": "In-field cotton detection via region-based semantic image segmentation", "pub_year": "2016"}, "filled": false, "author_pub_id": "lTUM3B0AAAAJ:u-x6o8ySG0sC", "num_citations": 102, "citedby_url": "https://scholar.google.com/scholar?oi=bibs&hl=en&cites=3138969405844617547", "cites_id": ["3138969405844617547"]}, "lTUM3B0AAAAJ:IjCSPb-OGe4C": {"container_type": "Publication", "source": "AUTHOR_PUBLICATION_ENTRY", "bib": {"title": "Fine-grained maize tassel trait characterization with multi-view representations", "pub_year": "2015"}, "filled": false, "author_pub_id": "lTUM3B0AAAAJ:IjCSPb-OGe4C", "num_citations": 74, "citedby_url": "https://scholar.google.com/scholar?oi=bibs&hl=en&cites=13720171569078564936", "cites_id": ["13720171569078564936"]}, "lTUM3B0AAAAJ:zYLM7Y9cAGgC": {"container_type": "Publication", "source": "AUTHOR_PUBLICATION_ENTRY", "bib": {"title": "Region-based colour modelling for joint crop and maize tassel segmentation", "pub_year": "2016"}, "filled": false, "author_pub_id": "lTUM3B0AAAAJ:zYLM7Y9cAGgC", "num_citations": 71, "citedby_url": "https://scholar.google.com/scholar?oi=bibs&hl=en&cites=15465214531814088585", "cites_id": ["15465214531814088585"]}, "lTUM3B0AAAAJ:8k81kl-MbHgC": {"container_type": "Publication", "source": "AUTHOR_PUBLICATION_ENTRY", "bib": {"title": "Sonicasl: An acoustic-based sign language gesture recognizer using earphones", "pub_year": "2021"}, "filled": false, "author_pub_id": "lTUM3B0AAAAJ:8k81kl-MbHgC", "num_citations": 64, "citedby_url": "https://scholar.google.com/scholar?oi=bibs&hl=en&cites=17497312081422348798", "cites_id": ["17497312081422348798"]}, "lTUM3B0AAAAJ:2osOgNQ5qMEC": {"container_type": "Publication", "source": "AUTHOR_PUBLICATION_ENTRY", "bib": {"title": "Sequential optimization for efficient high-quality object proposal generation", "pub_year": "2017"}, "filled": false, "author_pub_id": "lTUM3B0AAAAJ:2osOgNQ5qMEC", "num_citations": 45, "citedby_url": "https://scholar.google.com/scholar?oi=bibs&hl=en&cites=16362871080065443571", "cites_id": ["16362871080065443571"]}, "lTUM3B0AAAAJ:MXK_kJrjxJIC": {"container_type": "Publication", "source": "AUTHOR_PUBLICATION_ENTRY", "bib": {"title": "PIMNet: Physics-Infused Neural Network for Human Motion Prediction", "pub_year": "2022"}, "filled": false, "author_pub_id": "lTUM3B0AAAAJ:MXK_kJrjxJIC", "num_citations": 33, "citedby_url": "https://scholar.google.com/scholar?oi=bibs&hl=en&cites=12335050123080034581", "cites_id": ["12335050123080034581"]}, "lTUM3B0AAAAJ:Zph67rFs4hoC": {"container_type": "Publication", "source": "AUTHOR_PUBLICATION_ENTRY", "bib": {"title": "Defending against data-free model extraction by distributionally robust defensive training", "pub_year": "2023"}, "filled": false, "author_pub_id": "lTUM3B0AAAAJ:Zph67rFs4hoC", "num_citations": 24, "citedby_url": "https://scholar.google.com/scholar?oi=bibs&hl=en&cites=1352553956132625358", "cites_id": ["1352553956132625358"]}, "lTUM3B0AAAAJ:9yKSN-GCB0IC": {"container_type": "Publication", "source": "AUTHOR_PUBLICATION_ENTRY", "bib": {"title": "Toward good practices for fine-grained maize cultivar identification with filter-specific convolutional activations", "pub_year": "2016"}, "filled": false, "author_pub_id": "lTUM3B0AAAAJ:9yKSN-GCB0IC", "num_citations": 23, "citedby_url": "https://scholar.google.com/scholar?oi=bibs&hl=en&cites=14575295518138234221", "cites_id": ["14575295518138234221"]}, "lTUM3B0AAAAJ:3fE2CSJIrl8C": {"container_type": "Publication", "source": "AUTHOR_PUBLICATION_ENTRY", "bib": {"title": "MetaMix: Towards Corruption-Robust Continual Learning With Temporally Self-Adaptive Data Transformation", "pub_year": "2023"}, "filled": false, "author_pub_id": "lTUM3B0AAAAJ:3fE2CSJIrl8C", "num_citations": 21, "citedby_url": "https://scholar.google.com/scholar?oi=bibs&hl=en&cites=15345112654141971755", "cites_id": ["15345112654141971755"]}, "lTUM3B0AAAAJ:u5HHmVD_uO8C": {"container_type": "Publication", "source": "AUTHOR_PUBLICATION_ENTRY", "bib": {"title": "Towards fine-grained maize tassel flowering status recognition: Dataset, theory and practice", "pub_year": "2017"}, "filled": false, "author_pub_id": "lTUM3B0AAAAJ:u5HHmVD_uO8C", "num_citations": 21, "citedby_url": "https://scholar.google.com/scholar?oi=bibs&hl=en&cites=2961265856256389591", "cites_id": ["2961265856256389591"]}, "lTUM3B0AAAAJ:roLk4NBRz8UC": {"container_type": "Publication", "source": "AUTHOR_PUBLICATION_ENTRY", "bib": {"title": "Cp-nas: Child-parent neural architecture search for 1-bit cnns", "pub_year": "2021"}, "filled": false, "author_pub_id": "lTUM3B0AAAAJ:roLk4NBRz8UC", "num_citations": 20, "citedby_url": "https://scholar.google.com/scholar?oi=bibs&hl=en&cites=8489491699663594876", "cites_id": ["8489491699663594876"]}, "lTUM3B0AAAAJ:UeHWp8X0CEIC": {"container_type": "Publication", "source": "AUTHOR_PUBLICATION_ENTRY", "bib": {"title": "Joint crop and tassel segmentation in the wild", "pub_year": "2015"}, "filled": false, "author_pub_id": "lTUM3B0AAAAJ:UeHWp8X0CEIC", "num_citations": 16, "citedby_url": "https://scholar.google.com/scholar?oi=bibs&hl=en&cites=9546117147243248798", "cites_id": ["9546117147243248798"]}, "lTUM3B0AAAAJ:5nxA0vEk-isC": {"container_type": "Publication", "source": "AUTHOR_PUBLICATION_ENTRY", "bib": {"title": "PB-GCN: Progressive binary graph convolutional networks for skeleton-based action recognition", "pub_year": "2022"}, "filled": false, "author_pub_id": "lTUM3B0AAAAJ:5nxA0vEk-isC", "num_citations": 14, "citedby_url": "https://scholar.google.com/scholar?oi=bibs&hl=en&cites=4962884988256324708", "cites_id": ["4962884988256324708"]}, "lTUM3B0AAAAJ:Y0pCki6q_DkC": {"container_type": "Publication", "source": "AUTHOR_PUBLICATION_ENTRY", "bib": {"title": "Two-dimensional subspace alignment for convolutional activations adaptation", "pub_year": "2017"}, "filled": false, "author_pub_id": "lTUM3B0AAAAJ:Y0pCki6q_DkC", "num_citations": 13, "citedby_url": "https://scholar.google.com/scholar?oi=bibs&hl=en&cites=17226562494181132442", "cites_id": ["17226562494181132442"]}, "lTUM3B0AAAAJ:d1gkVwhDpl0C": {"container_type": "Publication", "source": "AUTHOR_PUBLICATION_ENTRY", "bib": {"title": "A novel denoising autoencoder assisted segmentation algorithm for cotton field", "pub_year": "2015"}, "filled": false, "author_pub_id": "lTUM3B0AAAAJ:d1gkVwhDpl0C", "num_citations": 9, "citedby_url": "https://scholar.google.com/scholar?oi=bibs&hl=en&cites=5348949139925818787", "cites_id": ["5348949139925818787"]}, "lTUM3B0AAAAJ:UebtZRa9Y70C": {"container_type": "Publication", "source": "AUTHOR_PUBLICATION_ENTRY", "bib": {"title": "System and method for automated learning from sensors", "pub_year": "2022"}, "filled": false, "author_pub_id": "lTUM3B0AAAAJ:UebtZRa9Y70C", "num_citations": 8, "citedby_url": "https://scholar.google.com/scholar?oi=bibs&hl=en&cites=15249933819459511869", "cites_id": ["15249933819459511869"]}, "lTUM3B0AAAAJ:Se3iqnhoufwC": {"container_type": "Publication", "source": "AUTHOR_PUBLICATION_ENTRY", "bib": {"title": "System and method for vision-based joint action and pose motion forecasting", "pub_year": "2021"}, "filled": false, "author_pub_id": "lTUM3B0AAAAJ:Se3iqnhoufwC", "num_citations": 7, "citedby_url": "https://scholar.google.com/scholar?oi=bibs&hl=en&cites=4494104399024281784", "cites_id": ["4494104399024281784"]}, "lTUM3B0AAAAJ:Tyk-4Ss8FVUC": {"container_type": "Publication", "source": "AUTHOR_PUBLICATION_ENTRY", "bib": {"title": "Fine-grained maize cultivar identification using filter-specific convolutional activations", "pub_year": "2016"}, "filled": false, "author_pub_id": "lTUM3B0AAAAJ:Tyk-4Ss8FVUC", "num_citations": 6, "citedby_url": "https://scholar.google.com/scholar?oi=bibs&hl=en&cites=16808819789497103399", "cites_id": ["16808819789497103399"]}, "lTUM3B0AAAAJ:_FxGoFyzp5QC": {"container_type": "Publication", "source": "AUTHOR_PUBLICATION_ENTRY", "bib": {"title": "What and How? Jointly Forecasting Human Action and Pose", "pub_year": "2021"}, "filled": false, "author_pub_id": "lTUM3B0AAAAJ:_FxGoFyzp5QC", "num_citations": 5, "citedby_url": "https://scholar.google.com/scholar?oi=bibs&hl=en&cites=17184355750284502240", "cites_id": ["17184355750284502240"]}, "lTUM3B0AAAAJ:YsMSGLbcyi4C": {"container_type": "Publication", "source": "AUTHOR_PUBLICATION_ENTRY", "bib": {"title": "Selecting Informative Frames for Action Recognition with Partial Observations", "pub_year": "2018"}, "filled": false, "author_pub_id": "lTUM3B0AAAAJ:YsMSGLbcyi4C", "num_citations": 4, "citedby_url": "https://scholar.google.com/scholar?oi=bibs&hl=en&cites=14711070082332390041", "cites_id": ["14711070082332390041"]}, "lTUM3B0AAAAJ:YOwf2qJgpHMC": {"container_type": "Publication", "source": "AUTHOR_PUBLICATION_ENTRY", "bib": {"title": "UniMotion: Bridging 2D and 3D Representations for Human Motion Prediction", "pub_year": "2025"}, "filled": false, "author_pub_id": "lTUM3B0AAAAJ:YOwf2qJgpHMC", "num_citations": 1, "citedby_url": "https://scholar.google.com/scholar?oi=bibs&hl=en&cites=11322693595551143575", "cites_id": ["11322693595551143575"]}, "lTUM3B0AAAAJ:_kc_bZDykSQC": {"container_type": "Publication", "source": "AUTHOR_PUBLICATION_ENTRY", "bib": {"title": "Multimodal Drivers of Attention Interruption to Baby Product Video Ads", "pub_year": "2024"}, "filled": false, "author_pub_id": "lTUM3B0AAAAJ:_kc_bZDykSQC", "num_citations": 1, "citedby_url": "https://scholar.google.com/scholar?oi=bibs&hl=en&cites=17016207172713667662", "cites_id": ["17016207172713667662"]}, "lTUM3B0AAAAJ:kNdYIx-mwKoC": {"container_type": "Publication", "source": "AUTHOR_PUBLICATION_ENTRY", "bib": {"title": "Make memory buffer stronger in continual learning: A continuous neural transformation approach", "pub_year": "2022"}, "filled": false, "author_pub_id": "lTUM3B0AAAAJ:kNdYIx-mwKoC", "num_citations": 1, "citedby_url": "https://scholar.google.com/scholar?oi=bibs&hl=en&cites=15178557777951040245", "cites_id": ["15178557777951040245"]}, "lTUM3B0AAAAJ:WF5omc3nYNoC": {"container_type": "Publication", "source": "AUTHOR_PUBLICATION_ENTRY", "bib": {"title": "Cam-Net: Compressed Attentive Multi-Granularity Network For Dynamic Scene Classification", "pub_year": "2020"}, "filled": false, "author_pub_id": "lTUM3B0AAAAJ:WF5omc3nYNoC", "num_citations": 1, "citedby_url": "https://scholar.google.com/scholar?oi=bibs&hl=en&cites=12638323349356383547", "cites_id": ["12638323349356383547"]}, "lTUM3B0AAAAJ:ufrVoPGSRksC": {"container_type": "Publication", "source": "AUTHOR_PUBLICATION_ENTRY", "bib": {"title": "CP-NAS: Child-Parent Neural Architecture Search for Binary Neural Networks", "pub_year": "2020"}, "filled": false, "author_pub_id": "lTUM3B0AAAAJ:ufrVoPGSRksC", "num_citations": 1, "citedby_url": "https://scholar.google.com/scholar?oi=bibs&hl=en&cites=8413256969518818952", "cites_id": ["8413256969518818952"]}, "lTUM3B0AAAAJ:ULOm3_A8WrAC": {"container_type": "Publication", "source": "AUTHOR_PUBLICATION_ENTRY", "bib": {"title": "System and method for performing unified human motion prediction (HMP) for 2D and 3D poses", "pub_year": "2025"}, "filled": false, "author_pub_id": "lTUM3B0AAAAJ:ULOm3_A8WrAC", "num_citations": 0}, "lTUM3B0AAAAJ:4TOpqqG69KYC": {"container_type": "Publication", "source": "AUTHOR_PUBLICATION_ENTRY", "bib": {"title": "Experimenting with Affective Computing Models in Video Interviews with Spanish-speaking Older Adults", "pub_year": "2025"}, "filled": false, "author_pub_id": "lTUM3B0AAAAJ:4TOpqqG69KYC", "num_citations": 0}, "lTUM3B0AAAAJ:KlAtU1dfN6UC": {"container_type": "Publication", "source": "AUTHOR_PUBLICATION_ENTRY", "bib": {"title": "Multimodal Human Action and Motion Prediction", "pub_year": "2023"}, "filled": false, "author_pub_id": "lTUM3B0AAAAJ:KlAtU1dfN6UC", "num_citations": 0}, "lTUM3B0AAAAJ:hqOjcs7Dif8C": {"container_type": "Publication", "source": "AUTHOR_PUBLICATION_ENTRY", "bib": {"title": "System and method for vision-based joint action and pose motion forecasting", "pub_year": "2022"}, "filled": false, "author_pub_id": "lTUM3B0AAAAJ:hqOjcs7Dif8C", "num_citations": 0}}, "citedby5y": 493, "hindex": 14, "hindex5y": 13, "i10index": 15, "i10index5y": 13, "cites_per_year": {"2016": 12, "2017": 31, "2018": 41, "2019": 58, "2020": 89, "2021": 73, "2022": 80, "2023": 110, "2024": 107, "2025": 116, "2026": 7}, "updated": "2026-02-14 08:37:08.041388"}